pytorchvideo/__init__.py
pytorchvideo/accelerator/__init__.py
pytorchvideo/accelerator/deployment/__init__.py
pytorchvideo/accelerator/deployment/common/__init__.py
pytorchvideo/accelerator/deployment/common/model_transmuter.py
pytorchvideo/accelerator/deployment/mobile_cpu/__init__.py
pytorchvideo/accelerator/deployment/mobile_cpu/transmuter/__init__.py
pytorchvideo/accelerator/deployment/mobile_cpu/transmuter/transmuter_mobile_cpu.py
pytorchvideo/accelerator/deployment/mobile_cpu/utils/__init__.py
pytorchvideo/accelerator/deployment/mobile_cpu/utils/model_conversion.py
pytorchvideo/accelerator/efficient_blocks/__init__.py
pytorchvideo/accelerator/efficient_blocks/efficient_block_base.py
pytorchvideo/accelerator/efficient_blocks/no_op_convert_block.py
pytorchvideo/data/__init__.py
pytorchvideo/data/ava.py
pytorchvideo/data/charades.py
pytorchvideo/data/clip_sampling.py
pytorchvideo/data/dataset_manifest_utils.py
pytorchvideo/data/decoder.py
pytorchvideo/data/domsev.py
pytorchvideo/data/encoded_video.py
pytorchvideo/data/encoded_video_decord.py
pytorchvideo/data/encoded_video_pyav.py
pytorchvideo/data/encoded_video_torchvision.py
pytorchvideo/data/epic_kitchen_forecasting.py
pytorchvideo/data/epic_kitchen_recognition.py
pytorchvideo/data/frame_video.py
pytorchvideo/data/hmdb51.py
pytorchvideo/data/json_dataset.py
pytorchvideo/data/kinetics.py
pytorchvideo/data/labeled_video_dataset.py
pytorchvideo/data/labeled_video_paths.py
pytorchvideo/data/ssv2.py
pytorchvideo/data/ucf101.py
pytorchvideo/data/utils.py
pytorchvideo/data/video.py
pytorchvideo/data/ego4d/__init__.py
pytorchvideo/data/ego4d/ego4d_dataset.py
pytorchvideo/data/ego4d/utils.py
pytorchvideo/data/epic_kitchen/__init__.py
pytorchvideo/data/epic_kitchen/epic_kitchen_dataset.py
pytorchvideo/data/epic_kitchen/utils.py
pytorchvideo/layers/__init__.py
pytorchvideo/layers/attention.py
pytorchvideo/layers/attention_torchscript.py
pytorchvideo/layers/batch_norm.py
pytorchvideo/layers/convolutions.py
jj_pytorchvideo-0.1.5.dist-info/LICENSE
jj_pytorchvideo-0.1.5.dist-info/METADATA
jj_pytorchvideo-0.1.5.dist-info/WHEEL
jj_pytorchvideo-0.1.5.dist-info/top_level.txt
jj_pytorchvideo-0.1.5.dist-info/RECORD
